{"events":[{"defined_class":"com.example.MainTest","event":"call","id":48,"lineno":43,"method_id":"testTwoSameBooksAndSingleDifferent","path":"com/example/MainTest.java","receiver":{"class":"com.example.MainTest","object_id":1745701482,"value":"com.example.MainTest@680d4a6a"},"static":false,"thread_id":1},{"defined_class":"com.example.Cart","event":"call","id":49,"lineno":25,"method_id":"addItems","parameters":[{"class":"[Lcom.example.Book;","kind":"req","name":"items","object_id":49299717,"value":"[Lcom.example.Book;@2f04105"}],"path":"com/example/Cart.java","receiver":{"class":"com.example.Cart","object_id":814753967,"value":"com.example.Cart@309028af"},"static":false,"thread_id":1},{"elapsed":1.40543E-5,"event":"return","id":50,"parent_id":49,"thread_id":1},{"defined_class":"com.example.Cart","event":"call","id":51,"lineno":34,"method_id":"calculateBestPrice","path":"com/example/Cart.java","receiver":{"class":"com.example.Cart","object_id":814753967,"value":"com.example.Cart@309028af"},"static":false,"thread_id":1},{"defined_class":"com.example.Cart","event":"call","id":52,"lineno":82,"method_id":"getBooksGroupedAndSorted","parameters":[{"class":"java.util.ArrayList","kind":"req","name":"listOfBooks","object_id":1917607102,"value":"[Piedra filosofal, Piedra filosofal, Orden fenix]"}],"path":"com/example/Cart.java","receiver":{"class":"com.example.Cart","object_id":814753967,"value":"com.example.Cart@309028af"},"static":false,"thread_id":1},{"defined_class":"com.example.Cart$1","event":"call","id":53,"lineno":101,"method_id":"compare","parameters":[{"class":"java.util.HashMap$Node","kind":"req","name":"e1","object_id":1880102535,"value":"Orden fenix=[Orden fenix]"},{"class":"java.util.HashMap$Node","kind":"req","name":"e2","object_id":1894287849,"value":"Piedra filosofal=[Piedra filosofal, Piedra filosofal]"}],"path":"com/example/Cart.java","receiver":{"class":"com.example.Cart$1","object_id":1099694603,"value":"com.example.Cart$1@418c020b"},"static":false,"thread_id":1},{"elapsed":1.55579E-5,"event":"return","id":54,"parent_id":53,"return_value":{"class":"java.lang.Integer","object_id":545872389,"value":"1"},"thread_id":1},{"elapsed":4.48578E-5,"event":"return","id":55,"parent_id":52,"return_value":{"class":"java.util.LinkedHashMap","object_id":1362435880,"value":"{Piedra filosofal=[Piedra filosofal, Piedra filosofal], Orden fenix=[Orden fenix]}"},"thread_id":1},{"defined_class":"com.example.Cart","event":"call","id":56,"lineno":50,"method_id":"recursiveMaxDiscount","parameters":[{"class":"java.util.LinkedHashMap","kind":"req","name":"booksGrouped","object_id":1362435880,"value":"{Piedra filosofal=[Piedra filosofal, Piedra filosofal], Orden fenix=[Orden fenix]}"},{"class":"java.lang.Integer","kind":"req","name":"currentGroup","object_id":333392964,"value":"0"}],"path":"com/example/Cart.java","receiver":{"class":"com.example.Cart","object_id":814753967,"value":"com.example.Cart@309028af"},"static":false,"thread_id":1},{"defined_class":"com.example.Cart","event":"call","id":57,"lineno":72,"method_id":"getBooksCopy","parameters":[{"class":"java.util.LinkedHashMap","kind":"req","name":"list","object_id":1362435880,"value":"{Piedra filosofal=[Piedra filosofal, Piedra filosofal], Orden fenix=[Orden fenix]}"}],"path":"com/example/Cart.java","receiver":{"class":"com.example.Cart","object_id":814753967,"value":"com.example.Cart@309028af"},"static":false,"thread_id":1},{"elapsed":1.41416E-5,"event":"return","id":58,"parent_id":57,"return_value":{"class":"java.util.LinkedHashMap","object_id":560041895,"value":"{Piedra filosofal=[Piedra filosofal, Piedra filosofal], Orden fenix=[Orden fenix]}"},"thread_id":1},{"defined_class":"com.example.Cart","event":"call","id":59,"lineno":50,"method_id":"recursiveMaxDiscount","parameters":[{"class":"java.util.LinkedHashMap","kind":"req","name":"booksGrouped","object_id":560041895,"value":"{Piedra filosofal=[Piedra filosofal]}"},{"class":"java.lang.Integer","kind":"req","name":"currentGroup","object_id":142684237,"value":"2"}],"path":"com/example/Cart.java","receiver":{"class":"com.example.Cart","object_id":814753967,"value":"com.example.Cart@309028af"},"static":false,"thread_id":1},{"elapsed":1.04614E-5,"event":"return","id":60,"parent_id":59,"return_value":{"class":"java.lang.Float","object_id":368242083,"value":"0.8"},"thread_id":1},{"elapsed":6.21244E-5,"event":"return","id":61,"parent_id":56,"return_value":{"class":"java.lang.Float","object_id":885991756,"value":"0.8"},"thread_id":1},{"elapsed":1.360002E-4,"event":"return","id":62,"parent_id":51,"return_value":{"class":"java.lang.Float","object_id":1299885218,"value":"23.2"},"thread_id":1},{"elapsed":1.771045E-4,"event":"return","id":63,"parent_id":48,"thread_id":1}],"classMap":[{"children":[{"children":[{"children":[{"labels":[],"location":"com/example/MainTest.java:43","name":"testTwoSameBooksAndSingleDifferent","static":false,"type":"function"}],"location":"com/example/MainTest.java","name":"MainTest","static":false,"type":"class"},{"children":[{"labels":[],"location":"com/example/Cart.java:50","name":"recursiveMaxDiscount","static":false,"type":"function"},{"labels":[],"location":"com/example/Cart.java:34","name":"calculateBestPrice","static":false,"type":"function"},{"labels":[],"location":"com/example/Cart.java:82","name":"getBooksGroupedAndSorted","static":false,"type":"function"},{"labels":[],"location":"com/example/Cart.java:72","name":"getBooksCopy","static":false,"type":"function"},{"labels":[],"location":"com/example/Cart.java:25","name":"addItems","static":false,"type":"function"}],"location":"com/example/Cart.java","name":"Cart","static":false,"type":"class"},{"children":[{"labels":[],"location":"com/example/Cart.java:101","name":"compare","static":false,"type":"function"}],"location":"com/example/Cart.java","name":"Cart$1","static":false,"type":"class"}],"name":"example","type":"package"}],"name":"com","type":"package"}],"version":"1.2","metadata":{"name":"Main test two same books and single different","app":"demo","language":{"name":"java","version":"17.0.10+11-LTS-240","engine":"Java HotSpot(TM) 64-Bit Server VM"},"client":{"name":"appmap-java","url":"https://github.com/appland/appmap-java"},"recorder":{"name":"junit","type":"tests"},"recording":{"defined_class":"com.example.MainTest","method_id":"testTwoSameBooksAndSingleDifferent"},"source_location":"com/example/MainTest.java:43","frameworks":[{"name":"junit","version":"4"}],"test_status":"succeeded"},"eventUpdates":{}}